Discord_Tools/__init__.py
Discord_Tools/defs.py
Discord_Tools/errors.py
Discord_Tools/main.py
Discord_Tools/util.py
Discord_Tools/voice.py
Discord_Tools-1.7.dist-info/LICENSE
Discord_Tools-1.7.dist-info/METADATA
Discord_Tools-1.7.dist-info/WHEEL
Discord_Tools-1.7.dist-info/top_level.txt
Discord_Tools-1.7.dist-info/RECORD
